<?xml version="1.0" encoding="UTF-8"?>
<beans:beans xmlns="http://www.springframework.org/schema/security"
             xmlns:beans="http://www.springframework.org/schema/beans"
             xmlns:xsi="http://www.w3.org/2001/XMLSchema-instance"
             xsi:schemaLocation="http://www.springframework.org/schema/beans
           http://www.springframework.org/schema/beans/spring-beans-4.1.xsd
           http://www.springframework.org/schema/security
            http://www.springframework.org/schema/security/spring-security-3.2.xsd">

    <http pattern="/loginPage" security="none"/>
    <http pattern="/loginFailed" security="none"/>
    <http pattern="/configuration/initialConfiguration" security="none"/>
    <http pattern="favicon.ico" security="none"/>
    <http pattern="/rest/*" security="none"/>

    <!--todo introduce public and private images in cms-->
    <http pattern="/newsImages/*" security="none"/>
    <http pattern="/blogPostImages/*" security="none"/>

    <http auto-config="false" authentication-manager-ref="cmsAuthorization" pattern="/*"
          entry-point-ref="cmsAuthenticationEntryPoint">
        <intercept-url pattern="/*" access="ROLE_CWSFE_CMS_ADMIN"/>
        <!--<session-management invalid-session-url="/timeout.htm"/>-->
        <access-denied-handler error-page="/loginFailed"/>
        <logout logout-success-url="/loginPage" invalidate-session="true"
                logout-url="/logout"/>
        <!--logout-url="/j_spring_security_logout"/>-->
        <custom-filter ref="cmsAuthenticationProcessingFilter" position="FORM_LOGIN_FILTER"/>
    </http>

    <authentication-manager id="cmsAuthorization">
        <authentication-provider ref="cmsAuthenticationProvider"/>
    </authentication-manager>

    <beans:bean id="cmsAuthenticationProvider" class="eu.com.cwsfe.cms.login.CmsAuthProvider"/>

    <beans:bean id="cmsAuthenticationEntryPoint"
                class="org.springframework.security.web.authentication.LoginUrlAuthenticationEntryPoint">
        <beans:property name="loginFormUrl" value="/loginPage"/>
    </beans:bean>

    <beans:bean id="cmsAuthenticationProcessingFilter" class="eu.com.cwsfe.cms.login.CmsAuthenticationProcessingFilter">
        <beans:property name="authenticationManager" ref="cmsAuthorization"/>
        <beans:property name="filterProcessesUrl" value="/cwsfe_cms_security_check"/>
        <beans:property name="authenticationFailureHandler" ref="cmsLoginFailureHandler"/>
        <beans:property name="authenticationSuccessHandler" ref="cmsLoginSuccessHandler"/>
    </beans:bean>

    <beans:bean id="cmsLoginSuccessHandler"
                class="org.springframework.security.web.authentication.SavedRequestAwareAuthenticationSuccessHandler">
        <beans:property name="defaultTargetUrl" value="/Main"/>
        <beans:property name="alwaysUseDefaultTargetUrl" value="true"/>
    </beans:bean>

    <beans:bean id="cmsLoginFailureHandler"
                class="org.springframework.security.web.authentication.SimpleUrlAuthenticationFailureHandler">
        <beans:property name="defaultFailureUrl" value="/loginFailed"/>
    </beans:bean>

</beans:beans>
